[
  {
    "product": "Stripchat",
    "placeholder_url": "https://example.com/aff/stripchat",
    "cta": "Try Stripchat"
  },
  {
    "product": "Chaturbate",
    "placeholder_url": "https://chaturbate.com/in/?tour=grq0&campaign=aoQgT&track=skeepy83_generic",
    "cta": "Try Chaturbate"
  },
  {
    "product": "LiveJasmin",
    "placeholder_url": "https://www.livejasmin.com/?psid=Skeepy83",
    "cta": "Try LiveJasmin"
  },
  {
    "product": "Flirt4Free",
    "placeholder_url": "https://example.com/aff/flirt4free",
    "cta": "Try Flirt4Free"
  }
]